chplot
