Metadata-Version: 2.1
Name: chplot
Version: 1.0.0.post1
Summary: Fast plot any math expression
Home-page: https://www.github.com/charon25/Chplot
Download-URL: https://github.com/charon25/Chplot/archive/refs/tags/v1.0.0.tar.gz
Author: Paul 'charon25' Kern
License: MIT
Requires-Python: >=3.9
License-File: LICENSE
